aws_session_management/__init__.py
aws_session_management/aws_session_management.py
aws_session_management-0.0.8.dist-info/LICENSE
aws_session_management-0.0.8.dist-info/METADATA
aws_session_management-0.0.8.dist-info/WHEEL
aws_session_management-0.0.8.dist-info/top_level.txt
aws_session_management-0.0.8.dist-info/RECORD
