Metadata-Version: 2.1
Name: aws-session-management
Version: 0.0.8
Summary: AWS Session Management
Home-page: https://github.com/deromka/aws-session-management
Author: Roman Dembitsky
Author-email: romande@gmail.com
License: UNKNOWN
Platform: UNKNOWN
Classifier: Programming Language :: Python :: 3
Classifier: License :: OSI Approved :: MIT License
Classifier: Operating System :: OS Independent
Requires-Python: >=3.7
